.coveragerc
CHANGES
COPYING
LICENSE
MANIFEST.in
Makefile
README
README.rst
VERSION.txt
buildout.cfg
classifiers.txt
ez_setup.py
requirements.in
requirements.txt
setup.cfg
setup.py
stdeb.cfg
tox.ini
tox.ini.in
requirements/dev.in
requirements/dev.txt
requirements/docs.in
requirements/docs.txt
requirements/lint.in
requirements/lint.txt
requirements/test.in
requirements/test.txt
src/README.rst
src/hwp5/COPYING
src/hwp5/README
src/hwp5/VERSION.txt
src/hwp5/__init__.py
src/hwp5/binspec.py
src/hwp5/bintype.py
src/hwp5/charsets.py
src/hwp5/cli.py
src/hwp5/compressed.py
src/hwp5/dataio.py
src/hwp5/distdoc.py
src/hwp5/errors.py
src/hwp5/filestructure.py
src/hwp5/hwp5html.py
src/hwp5/hwp5odt.py
src/hwp5/hwp5proc.py
src/hwp5/hwp5txt.py
src/hwp5/hwp5view.py
src/hwp5/importhelper.py
src/hwp5/msoleprops.py
src/hwp5/recordstream.py
src/hwp5/summaryinfo.py
src/hwp5/tagids.py
src/hwp5/treeop.py
src/hwp5/utils.py
src/hwp5/xmldump_flat.py
src/hwp5/xmlformat.py
src/hwp5/xmlmodel.py
src/hwp5/zlib_raw_codec.py
src/hwp5/binmodel/__init__.py
src/hwp5/binmodel/_shared.py
src/hwp5/binmodel/controlchar.py
src/hwp5/binmodel/tagid16_document_properties.py
src/hwp5/binmodel/tagid17_id_mappings.py
src/hwp5/binmodel/tagid18_bin_data.py
src/hwp5/binmodel/tagid19_face_name.py
src/hwp5/binmodel/tagid20_border_fill.py
src/hwp5/binmodel/tagid21_char_shape.py
src/hwp5/binmodel/tagid22_tab_def.py
src/hwp5/binmodel/tagid23_numbering.py
src/hwp5/binmodel/tagid24_bullet.py
src/hwp5/binmodel/tagid25_para_shape.py
src/hwp5/binmodel/tagid26_style.py
src/hwp5/binmodel/tagid27_doc_data.py
src/hwp5/binmodel/tagid28_distribute_doc_data.py
src/hwp5/binmodel/tagid30_compatible_document.py
src/hwp5/binmodel/tagid31_layout_compatibility.py
src/hwp5/binmodel/tagid32_unknown.py
src/hwp5/binmodel/tagid50_para_header.py
src/hwp5/binmodel/tagid51_para_text.py
src/hwp5/binmodel/tagid52_para_char_shape.py
src/hwp5/binmodel/tagid53_para_line_seg.py
src/hwp5/binmodel/tagid54_para_range_tag.py
src/pyhwp.egg-info/PKG-INFO
src/pyhwp.egg-info/SOURCES.txt
src/pyhwp.egg-info/dependency_links.txt
src/pyhwp.egg-info/entry_points.txt
src/pyhwp.egg-info/not-zip-safe
src/pyhwp.egg-info/requires.txt
src/pyhwp.egg-info/top_level.txt